{
  "1": {
    "GBP": {
      "msi-activities": {
        "2016": 4380746.0,
        "2017": 1242622.0,
        "2018": 27609698.0,
        "2019": 61568777.84,
        "2020": 56020635.86,
        "2021": 25503431.0,
        "2013": 3273634.0,
        "2014": 2724730.0,
        "2015": 2927889.0,
        "2022": 9198174.0,
        "2023": 8378851.0,
        "2024": 2220000.0
      }
    },
    "EUR": {
      "msi-activities": {
        "2017": 917362.0,
        "2018": 4296073.0,
        "2019": 2536350.0
      }
    },
    "XOF": {
      "msi-activities": {
        "2016": 1051294320.0,
        "2017": 952511905.0,
        "2018": 975553318.0,
        "2019": 956382624.0
      }
    }
  },
  "2": {
    "GBP": {
      "msi-activities": {
        "2017": 36461322.0,
        "2018": 17417645.0
      }
    }
  },
  "null": {
    "GBP": {
      "msi-activities": {
        "2021": 7448510.29
      }
    }
  }
}