{
  "2": {
    ".//@default-currency": {
      "pontis-by": {
        "EUR": 1
      },
      "pontis-tn": {
        "EUR": 2
      },
      "pontis-eg": {
        "EUR": 1
      },
      "pontis-xk": {
        "EUR": 1
      },
      "pontis-md": {
        "EUR": 3
      },
      "pontis-ke": {
        "EUR": 3
      },
      "pontis-mk": {
        "EUR": 1
      },
      "pontis-sk": {
        "EUR": 3
      }
    },
    ".//activity-date/@type": {
      "pontis-by": {
        "2": 1,
        "4": 1
      },
      "pontis-tn": {
        "2": 2,
        "3": 1,
        "4": 1
      },
      "pontis-eg": {
        "2": 1,
        "4": 1
      },
      "pontis-xk": {
        "1": 1
      },
      "pontis-md": {
        "2": 3,
        "4": 1,
        "3": 1
      },
      "pontis-ke": {
        "2": 3,
        "3": 2,
        "4": 1
      },
      "pontis-mk": {
        "2": 1,
        "3": 1
      },
      "pontis-sk": {
        "2": 3,
        "3": 1,
        "4": 2
      }
    },
    ".//activity-status/@code": {
      "pontis-by": {
        "3": 1
      },
      "pontis-tn": {
        "3": 2
      },
      "pontis-eg": {
        "3": 1
      },
      "pontis-xk": {
        "1": 1
      },
      "pontis-md": {
        "3": 3
      },
      "pontis-ke": {
        "3": 2,
        "2": 1
      },
      "pontis-mk": {
        "3": 1
      },
      "pontis-sk": {
        "3": 3
      }
    },
    ".//budget/@status": {
      "pontis-by": {
        "1": 1
      },
      "pontis-tn": {
        "1": 2
      },
      "pontis-eg": {
        "1": 1
      },
      "pontis-xk": {
        "1": 1
      },
      "pontis-md": {
        "1": 3
      },
      "pontis-ke": {
        "1": 5
      },
      "pontis-mk": {
        "1": 1
      },
      "pontis-sk": {
        "1": 2
      }
    },
    ".//budget/@type": {
      "pontis-by": {
        "1": 1
      },
      "pontis-tn": {
        "1": 2
      },
      "pontis-eg": {
        "1": 1
      },
      "pontis-xk": {
        "1": 1
      },
      "pontis-md": {
        "1": 3
      },
      "pontis-ke": {
        "1": 5
      },
      "pontis-mk": {
        "1": 1
      },
      "pontis-sk": {
        "1": 2
      }
    },
    ".//budget/value/@currency": {
      "pontis-by": {
        "EUR": 1
      },
      "pontis-tn": {
        "EUR": 2
      },
      "pontis-eg": {
        "EUR": 1
      },
      "pontis-xk": {
        "EUR": 1
      },
      "pontis-md": {
        "EUR": 3
      },
      "pontis-ke": {
        "EUR": 5
      },
      "pontis-mk": {
        "EUR": 1
      },
      "pontis-sk": {
        "EUR": 2
      }
    },
    ".//collaboration-type/@code": {
      "pontis-by": {
        "1": 1
      },
      "pontis-tn": {
        "1": 2
      },
      "pontis-eg": {
        "1": 1
      },
      "pontis-xk": {
        "1": 1
      },
      "pontis-md": {
        "1": 3
      },
      "pontis-ke": {
        "1": 3
      },
      "pontis-mk": {
        "1": 1
      },
      "pontis-sk": {
        "1": 3
      }
    },
    ".//contact-info/@type": {
      "pontis-by": {
        "1": 1
      },
      "pontis-tn": {
        "1": 2
      },
      "pontis-eg": {
        "1": 1
      },
      "pontis-xk": {
        "1": 1
      },
      "pontis-md": {
        "1": 3
      },
      "pontis-ke": {
        "2": 3
      },
      "pontis-mk": {
        "1": 1
      },
      "pontis-sk": {
        "1": 3
      }
    },
    ".//default-aid-type[@vocabulary = '1' or not(@vocabulary)]/@code": {
      "pontis-by": {
        "C01": 1
      },
      "pontis-tn": {
        "C01": 2
      },
      "pontis-eg": {
        "C01": 1
      },
      "pontis-xk": {
        "C01": 1
      },
      "pontis-md": {
        "C01": 3
      },
      "pontis-ke": {
        "C01": 3
      },
      "pontis-mk": {
        "C01": 1
      },
      "pontis-sk": {
        "C01": 3
      }
    },
    ".//default-finance-type/@code": {
      "pontis-by": {
        "110": 1
      },
      "pontis-tn": {
        "110": 2
      },
      "pontis-eg": {
        "110": 1
      },
      "pontis-xk": {
        "110": 1
      },
      "pontis-md": {
        "110": 3
      },
      "pontis-ke": {
        "110": 3
      },
      "pontis-mk": {
        "110": 1
      },
      "pontis-sk": {
        "110": 2
      }
    },
    ".//default-flow-type/@code": {
      "pontis-by": {
        "10": 1
      },
      "pontis-tn": {
        "10": 2
      },
      "pontis-eg": {
        "10": 1
      },
      "pontis-xk": {
        "10": 1
      },
      "pontis-md": {
        "10": 3
      },
      "pontis-ke": {
        "10": 3
      },
      "pontis-mk": {
        "10": 1
      },
      "pontis-sk": {
        "10": 3
      }
    },
    ".//default-tied-status/@code": {
      "pontis-by": {
        "5": 1
      },
      "pontis-tn": {
        "5": 2
      },
      "pontis-eg": {
        "5": 1
      },
      "pontis-xk": {
        "5": 1
      },
      "pontis-md": {
        "5": 3
      },
      "pontis-ke": {
        "5": 3
      },
      "pontis-mk": {
        "5": 1
      },
      "pontis-sk": {
        "5": 3
      }
    },
    ".//description/@type": {
      "pontis-by": {
        "1": 1
      },
      "pontis-tn": {
        "2": 2,
        "1": 1
      },
      "pontis-eg": {
        "1": 1
      },
      "pontis-xk": {
        "2": 1,
        "1": 1
      },
      "pontis-md": {
        "1": 2
      },
      "pontis-ke": {
        "1": 3,
        "3": 1,
        "2": 1
      },
      "pontis-mk": {
        "2": 1,
        "3": 1
      },
      "pontis-sk": {
        "1": 3,
        "2": 2,
        "3": 1
      }
    },
    ".//document-link/@format": {
      "pontis-by": {
        "text/html": 1
      },
      "pontis-tn": {
        "text/html": 3
      },
      "pontis-eg": {
        "text/html": 1
      },
      "pontis-md": {
        "text/html": 2
      },
      "pontis-ke": {
        "text/html": 2
      },
      "pontis-mk": {
        "text/html": 1
      },
      "pontis-sk": {
        "text/html": 2,
        "application/vnd.anser-web-certificate-issue-initiation": 1
      }
    },
    ".//document-link/category/@code": {
      "pontis-by": {
        "A12": 1
      },
      "pontis-tn": {
        "A12": 3
      },
      "pontis-eg": {
        "A12": 1
      },
      "pontis-md": {
        "A12": 2
      },
      "pontis-ke": {
        "A12": 2
      },
      "pontis-mk": {
        "A12": 1
      },
      "pontis-sk": {
        "A12": 3
      }
    },
    ".//document-link/language/@code": {
      "pontis-by": {
        "en": 1
      },
      "pontis-tn": {
        "en": 3
      },
      "pontis-eg": {
        "en": 1
      },
      "pontis-md": {
        "en": 2
      },
      "pontis-ke": {
        "en": 2
      },
      "pontis-mk": {
        "en": 1
      },
      "pontis-sk": {
        "en": 3
      }
    },
    ".//location/location-reach/@code": {
      "pontis-by": {
        "1": 1
      },
      "pontis-tn": {
        "1": 2
      },
      "pontis-eg": {
        "1": 1
      },
      "pontis-xk": {
        "1": 1
      },
      "pontis-md": {
        "1": 2
      },
      "pontis-ke": {
        "1": 2
      },
      "pontis-mk": {
        "1": 3
      },
      "pontis-sk": {
        "1": 5
      }
    },
    ".//location/exactness/@code": {
      "pontis-by": {
        "2": 1
      },
      "pontis-tn": {
        "2": 1
      },
      "pontis-eg": {
        "2": 1
      },
      "pontis-xk": {
        "2": 1
      },
      "pontis-md": {
        "2": 1
      },
      "pontis-ke": {
        "2": 1
      },
      "pontis-mk": {
        "2": 3
      },
      "pontis-sk": {
        "2": 4
      }
    },
    ".//participating-org/@role": {
      "pontis-by": {
        "3": 1,
        "4": 1,
        "1": 1
      },
      "pontis-tn": {
        "3": 2,
        "4": 2,
        "1": 2
      },
      "pontis-eg": {
        "3": 1,
        "1": 1,
        "4": 1
      },
      "pontis-xk": {
        "3": 1,
        "1": 1,
        "4": 1
      },
      "pontis-md": {
        "3": 3,
        "1": 2,
        "4": 2
      },
      "pontis-ke": {
        "3": 3,
        "1": 3,
        "4": 3
      },
      "pontis-mk": {
        "3": 1,
        "4": 1,
        "1": 1
      },
      "pontis-sk": {
        "1": 3,
        "4": 5
      }
    },
    ".//participating-org/@type": {
      "pontis-by": {
        "80": 1,
        "60": 1,
        "10": 1
      },
      "pontis-tn": {
        "22": 2,
        "60": 2,
        "10": 2
      },
      "pontis-eg": {
        "10": 1,
        "60": 1
      },
      "pontis-xk": {
        "22": 1,
        "10": 1,
        "60": 1
      },
      "pontis-md": {
        "10": 3,
        "60": 3,
        "22": 1
      },
      "pontis-ke": {
        "22": 3,
        "10": 3,
        "60": 3
      },
      "pontis-mk": {
        "22": 1,
        "60": 1,
        "10": 1
      },
      "pontis-sk": {
        "10": 2,
        "60": 3
      }
    },
    ".//policy-marker[@vocabulary = '1' or not(@vocabulary)]/@code": {
      "pontis-by": {
        "3": 1
      },
      "pontis-tn": {
        "3": 2
      },
      "pontis-eg": {
        "3": 1
      },
      "pontis-xk": {
        "3": 1
      },
      "pontis-md": {
        "3": 3
      },
      "pontis-ke": {
        "3": 3
      },
      "pontis-mk": {
        "3": 1
      },
      "pontis-sk": {
        "3": 3
      }
    },
    ".//policy-marker/@significance": {
      "pontis-by": {
        "1": 1
      },
      "pontis-tn": {
        "1": 2
      },
      "pontis-eg": {
        "1": 1
      },
      "pontis-xk": {
        "1": 1
      },
      "pontis-md": {
        "1": 3
      },
      "pontis-ke": {
        "1": 3
      },
      "pontis-mk": {
        "1": 1
      },
      "pontis-sk": {
        "1": 3
      }
    },
    ".//recipient-country/@code": {
      "pontis-by": {
        "BY": 1
      },
      "pontis-tn": {
        "TN": 2
      },
      "pontis-eg": {
        "EG": 1,
        "TN": 1
      },
      "pontis-xk": {
        "XK": 1
      },
      "pontis-md": {
        "MD": 3
      },
      "pontis-ke": {
        "KE": 3
      },
      "pontis-mk": {
        "MK": 1,
        "RS": 1
      },
      "pontis-sk": {
        "SK": 3,
        "CY": 1,
        "IE": 1
      }
    },
    ".//reporting-org/@type": {
      "pontis-by": {
        "60": 1
      },
      "pontis-tn": {
        "60": 2
      },
      "pontis-eg": {
        "60": 1
      },
      "pontis-xk": {
        "60": 1
      },
      "pontis-md": {
        "60": 3
      },
      "pontis-ke": {
        "60": 3
      },
      "pontis-mk": {
        "60": 1
      },
      "pontis-sk": {
        "60": 3
      }
    },
    ".//result/@type": {
      "pontis-by": {
        "1": 1
      },
      "pontis-tn": {
        "1": 1
      },
      "pontis-md": {
        "1": 2
      },
      "pontis-ke": {
        "1": 5,
        "3": 1,
        "2": 1
      },
      "pontis-sk": {
        "1": 2
      }
    },
    ".//result/indicator/@measure": {
      "pontis-by": {
        "1": 1
      },
      "pontis-tn": {
        "1": 1
      },
      "pontis-md": {
        "1": 2
      },
      "pontis-ke": {
        "1": 7
      },
      "pontis-sk": {
        "1": 2
      }
    },
    ".//sector[@vocabulary = '1' or not(@vocabulary)]/@code": {
      "pontis-by": {
        "11110": 1
      },
      "pontis-tn": {
        "15150": 2
      },
      "pontis-eg": {
        "15150": 1
      },
      "pontis-xk": {
        "15150": 1
      },
      "pontis-md": {
        "15150": 3
      },
      "pontis-ke": {
        "11120": 1,
        "11130": 2,
        "11320": 5,
        "22040": 1
      },
      "pontis-mk": {
        "15150": 1
      },
      "pontis-sk": {
        "99820": 2,
        "11120": 1
      }
    },
    ".//sector/@vocabulary": {
      "pontis-by": {
        "1": 1
      },
      "pontis-tn": {
        "1": 2
      },
      "pontis-eg": {
        "1": 1
      },
      "pontis-xk": {
        "1": 1
      },
      "pontis-md": {
        "1": 3
      },
      "pontis-ke": {
        "1": 9
      },
      "pontis-mk": {
        "1": 1
      },
      "pontis-sk": {
        "1": 3
      }
    },
    ".//@xml:lang": {
      "pontis-by": {
        "en": 5
      },
      "pontis-tn": {
        "en": 15
      },
      "pontis-eg": {
        "en": 4
      },
      "pontis-xk": {
        "en": 2
      },
      "pontis-md": {
        "en": 12
      },
      "pontis-ke": {
        "en": 52
      },
      "pontis-mk": {
        "en": 9
      },
      "pontis-sk": {
        "en": 27
      }
    },
    ".//transaction/transaction-type/@code": {
      "pontis-tn": {
        "4": 1
      },
      "pontis-md": {
        "4": 2
      },
      "pontis-ke": {
        "1": 1,
        "2": 1,
        "3": 5,
        "4": 2
      },
      "pontis-mk": {
        "4": 1
      },
      "pontis-sk": {
        "4": 1
      }
    },
    ".//transaction/value/@currency": {
      "pontis-tn": {
        "EUR": 1
      },
      "pontis-md": {
        "EUR": 2
      },
      "pontis-ke": {
        "EUR": 2
      },
      "pontis-mk": {
        "EUR": 1
      },
      "pontis-sk": {
        "EUR": 1
      }
    },
    ".//transaction/disbursement-channel/@code": {
      "pontis-md": {
        "2": 2
      },
      "pontis-ke": {
        "4": 1,
        "2": 6,
        "3": 1
      }
    },
    ".//transaction/aid-type[@vocabulary = '1' or not(@vocabulary)]/@code": {
      "pontis-ke": {
        "C01": 7
      }
    },
    ".//transaction/finance-type/@code": {
      "pontis-ke": {
        "110": 7
      }
    },
    ".//transaction/flow-type/@code": {
      "pontis-ke": {
        "10": 7
      }
    },
    ".//transaction/provider-org/@type": {
      "pontis-ke": {
        "60": 1
      }
    },
    ".//transaction/receiver-org/@type": {
      "pontis-ke": {
        "22": 1
      }
    },
    ".//transaction/sector[@vocabulary = '1' or not(@vocabulary)]/@code": {
      "pontis-ke": {
        "11320": 5
      }
    },
    ".//transaction/sector/@vocabulary": {
      "pontis-ke": {
        "1": 5
      }
    },
    ".//transaction/tied-status/@code": {
      "pontis-ke": {
        "5": 7
      }
    }
  }
}