{
  ".//@default-currency": {
    "GBP": {
      "concernuk-activities": 38
    }
  },
  ".//@xml:lang": {
    "en": {
      "concernuk-activities": 38
    }
  },
  ".//activity-date/@type": {
    "1": {
      "concernuk-activities": 38
    },
    "2": {
      "concernuk-activities": 38
    },
    "3": {
      "concernuk-activities": 38
    },
    "4": {
      "concernuk-activities": 24
    }
  },
  ".//activity-status/@code": {
    "2": {
      "concernuk-activities": 24
    },
    "3": {
      "concernuk-activities": 14
    }
  },
  ".//budget/value/@currency": {
    "GBP": {
      "concernuk-activities": 96
    }
  },
  ".//collaboration-type/@code": {
    "1": {
      "concernuk-activities": 38
    }
  },
  ".//contact-info/@type": {
    "1": {
      "concernuk-activities": 38
    }
  },
  ".//default-aid-type[@vocabulary = '1' or not(@vocabulary)]/@code": {
    "C01": {
      "concernuk-activities": 38
    }
  },
  ".//default-finance-type/@code": {
    "110": {
      "concernuk-activities": 38
    }
  },
  ".//default-flow-type/@code": {
    "30": {
      "concernuk-activities": 38
    }
  },
  ".//default-tied-status/@code": {
    "5": {
      "concernuk-activities": 38
    }
  },
  ".//description/@type": {
    "1": {
      "concernuk-activities": 38
    }
  },
  ".//participating-org/@role": {
    "1": {
      "concernuk-activities": 38
    },
    "2": {
      "concernuk-activities": 38
    },
    "4": {
      "concernuk-activities": 38
    }
  },
  ".//participating-org/@type": {
    "10": {
      "concernuk-activities": 10
    },
    "21": {
      "concernuk-activities": 96
    },
    "70": {
      "concernuk-activities": 3
    },
    "22": {
      "concernuk-activities": 5
    }
  },
  ".//policy-marker/@significance": {
    "1": {
      "concernuk-activities": 38
    }
  },
  ".//policy-marker/@vocabulary": {
    "1": {
      "concernuk-activities": 38
    }
  },
  ".//policy-marker[@vocabulary = '1' or not(@vocabulary)]/@code": {
    "3": {
      "concernuk-activities": 38
    }
  },
  ".//recipient-country/@code": {
    "CD": {
      "concernuk-activities": 1
    },
    "SL": {
      "concernuk-activities": 6
    },
    "ZM": {
      "concernuk-activities": 1
    },
    "AF": {
      "concernuk-activities": 1
    },
    "PK": {
      "concernuk-activities": 1
    },
    "SY": {
      "concernuk-activities": 1
    },
    "KE": {
      "concernuk-activities": 4
    },
    "MW": {
      "concernuk-activities": 4
    },
    "SO": {
      "concernuk-activities": 7
    },
    "BI": {
      "concernuk-activities": 2
    },
    "BD": {
      "concernuk-activities": 5
    },
    "SD": {
      "concernuk-activities": 1
    },
    "ET": {
      "concernuk-activities": 2
    },
    "NP": {
      "concernuk-activities": 1
    },
    "YE": {
      "concernuk-activities": 1
    },
    "TD": {
      "concernuk-activities": 1
    },
    "LR": {
      "concernuk-activities": 1
    }
  },
  ".//reporting-org/@type": {
    "22": {
      "concernuk-activities": 38
    }
  },
  ".//result/@type": {
    "2": {
      "concernuk-activities": 17
    }
  },
  ".//result/indicator/@measure": {
    "2": {
      "concernuk-activities": 23
    },
    "1": {
      "concernuk-activities": 20
    }
  },
  ".//sector/@vocabulary": {
    "1": {
      "concernuk-activities": 68
    }
  },
  ".//sector[@vocabulary = '1' or not(@vocabulary)]/@code": {
    "14031": {
      "concernuk-activities": 5
    },
    "14032": {
      "concernuk-activities": 1
    },
    "12261": {
      "concernuk-activities": 8
    },
    "15180": {
      "concernuk-activities": 1
    },
    "12240": {
      "concernuk-activities": 4
    },
    "31166": {
      "concernuk-activities": 1
    },
    "74010": {
      "concernuk-activities": 7
    },
    "72010": {
      "concernuk-activities": 16
    },
    "15185": {
      "concernuk-activities": 1
    },
    "31120": {
      "concernuk-activities": 2
    },
    "31150": {
      "concernuk-activities": 2
    },
    "31192": {
      "concernuk-activities": 1
    },
    "31161": {
      "concernuk-activities": 2
    },
    "72040": {
      "concernuk-activities": 1
    },
    "73010": {
      "concernuk-activities": 1
    },
    "11220": {
      "concernuk-activities": 1
    },
    "11320": {
      "concernuk-activities": 1
    },
    "12220": {
      "concernuk-activities": 6
    },
    "31195": {
      "concernuk-activities": 1
    },
    "12110": {
      "concernuk-activities": 2
    },
    "11231": {
      "concernuk-activities": 2
    },
    "16011": {
      "concernuk-activities": 1
    },
    "15110": {
      "concernuk-activities": 1
    }
  },
  ".//transaction/transaction-type/@code": {
    "1": {
      "concernuk-activities": 179
    },
    "11": {
      "concernuk-activities": 38
    },
    "2": {
      "concernuk-activities": 37
    },
    "3": {
      "concernuk-activities": 183
    }
  },
  ".//transaction/value/@currency": {
    "GBP": {
      "concernuk-activities": 437
    }
  }
}