{
  "iati-activity": {
    "tbalert-activities": 3
  },
  "iati-activity/@default-currency": {
    "tbalert-activities": 3
  },
  "iati-activity/@hierarchy": {
    "tbalert-activities": 3
  },
  "iati-activity/@humanitarian": {
    "tbalert-activities": 2
  },
  "iati-activity/@last-updated-datetime": {
    "tbalert-activities": 3
  },
  "iati-activity/@{http://www.w3.org/XML/1998/namespace}lang": {
    "tbalert-activities": 2
  },
  "iati-activity/activity-date": {
    "tbalert-activities": 5
  },
  "iati-activity/activity-date/@iso-date": {
    "tbalert-activities": 5
  },
  "iati-activity/activity-date/@type": {
    "tbalert-activities": 5
  },
  "iati-activity/activity-date/narrative": {
    "tbalert-activities": 3
  },
  "iati-activity/activity-date/narrative/@{http://www.w3.org/XML/1998/namespace}lang": {
    "tbalert-activities": 1
  },
  "iati-activity/activity-status": {
    "tbalert-activities": 3
  },
  "iati-activity/activity-status/@code": {
    "tbalert-activities": 3
  },
  "iati-activity/budget": {
    "tbalert-activities": 8
  },
  "iati-activity/budget/@status": {
    "tbalert-activities": 7
  },
  "iati-activity/budget/@type": {
    "tbalert-activities": 8
  },
  "iati-activity/budget/period-end": {
    "tbalert-activities": 8
  },
  "iati-activity/budget/period-end/@iso-date": {
    "tbalert-activities": 8
  },
  "iati-activity/budget/period-start": {
    "tbalert-activities": 8
  },
  "iati-activity/budget/period-start/@iso-date": {
    "tbalert-activities": 8
  },
  "iati-activity/budget/value": {
    "tbalert-activities": 8
  },
  "iati-activity/budget/value/@currency": {
    "tbalert-activities": 1
  },
  "iati-activity/budget/value/@value-date": {
    "tbalert-activities": 7
  },
  "iati-activity/contact-info": {
    "tbalert-activities": 2
  },
  "iati-activity/contact-info/@type": {
    "tbalert-activities": 1
  },
  "iati-activity/contact-info/department": {
    "tbalert-activities": 1
  },
  "iati-activity/contact-info/department/narrative": {
    "tbalert-activities": 1
  },
  "iati-activity/contact-info/department/narrative/@{http://www.w3.org/XML/1998/namespace}lang": {
    "tbalert-activities": 1
  },
  "iati-activity/contact-info/email": {
    "tbalert-activities": 1
  },
  "iati-activity/contact-info/job-title": {
    "tbalert-activities": 1
  },
  "iati-activity/contact-info/job-title/narrative": {
    "tbalert-activities": 1
  },
  "iati-activity/contact-info/job-title/narrative/@{http://www.w3.org/XML/1998/namespace}lang": {
    "tbalert-activities": 1
  },
  "iati-activity/contact-info/mailing-address": {
    "tbalert-activities": 2
  },
  "iati-activity/contact-info/mailing-address/narrative": {
    "tbalert-activities": 2
  },
  "iati-activity/contact-info/mailing-address/narrative/@{http://www.w3.org/XML/1998/namespace}lang": {
    "tbalert-activities": 1
  },
  "iati-activity/contact-info/organisation": {
    "tbalert-activities": 2
  },
  "iati-activity/contact-info/organisation/narrative": {
    "tbalert-activities": 2
  },
  "iati-activity/contact-info/organisation/narrative/@{http://www.w3.org/XML/1998/namespace}lang": {
    "tbalert-activities": 1
  },
  "iati-activity/contact-info/person-name": {
    "tbalert-activities": 1
  },
  "iati-activity/contact-info/person-name/narrative": {
    "tbalert-activities": 1
  },
  "iati-activity/contact-info/person-name/narrative/@{http://www.w3.org/XML/1998/namespace}lang": {
    "tbalert-activities": 1
  },
  "iati-activity/contact-info/telephone": {
    "tbalert-activities": 1
  },
  "iati-activity/contact-info/website": {
    "tbalert-activities": 2
  },
  "iati-activity/default-aid-type": {
    "tbalert-activities": 3
  },
  "iati-activity/default-aid-type/@code": {
    "tbalert-activities": 3
  },
  "iati-activity/default-flow-type": {
    "tbalert-activities": 3
  },
  "iati-activity/default-flow-type/@code": {
    "tbalert-activities": 3
  },
  "iati-activity/description": {
    "tbalert-activities": 3
  },
  "iati-activity/description/@type": {
    "tbalert-activities": 2
  },
  "iati-activity/description/narrative": {
    "tbalert-activities": 3
  },
  "iati-activity/description/narrative/@{http://www.w3.org/XML/1998/namespace}lang": {
    "tbalert-activities": 1
  },
  "iati-activity/document-link": {
    "tbalert-activities": 4
  },
  "iati-activity/document-link/@format": {
    "tbalert-activities": 4
  },
  "iati-activity/document-link/@url": {
    "tbalert-activities": 4
  },
  "iati-activity/document-link/category": {
    "tbalert-activities": 4
  },
  "iati-activity/document-link/category/@code": {
    "tbalert-activities": 4
  },
  "iati-activity/document-link/language": {
    "tbalert-activities": 4
  },
  "iati-activity/document-link/language/@code": {
    "tbalert-activities": 4
  },
  "iati-activity/document-link/title": {
    "tbalert-activities": 4
  },
  "iati-activity/document-link/title/narrative": {
    "tbalert-activities": 4
  },
  "iati-activity/document-link/title/narrative/@{http://www.w3.org/XML/1998/namespace}lang": {
    "tbalert-activities": 1
  },
  "iati-activity/iati-identifier": {
    "tbalert-activities": 3
  },
  "iati-activity/participating-org": {
    "tbalert-activities": 8
  },
  "iati-activity/participating-org/@ref": {
    "tbalert-activities": 4
  },
  "iati-activity/participating-org/@role": {
    "tbalert-activities": 8
  },
  "iati-activity/participating-org/@type": {
    "tbalert-activities": 8
  },
  "iati-activity/participating-org/narrative": {
    "tbalert-activities": 8
  },
  "iati-activity/participating-org/narrative/@{http://www.w3.org/XML/1998/namespace}lang": {
    "tbalert-activities": 1
  },
  "iati-activity/recipient-country": {
    "tbalert-activities": 3
  },
  "iati-activity/recipient-country/@code": {
    "tbalert-activities": 3
  },
  "iati-activity/recipient-country/@percentage": {
    "tbalert-activities": 3
  },
  "iati-activity/recipient-country/narrative": {
    "tbalert-activities": 2
  },
  "iati-activity/recipient-country/narrative/@{http://www.w3.org/XML/1998/namespace}lang": {
    "tbalert-activities": 1
  },
  "iati-activity/reporting-org": {
    "tbalert-activities": 3
  },
  "iati-activity/reporting-org/@ref": {
    "tbalert-activities": 3
  },
  "iati-activity/reporting-org/@type": {
    "tbalert-activities": 3
  },
  "iati-activity/reporting-org/narrative": {
    "tbalert-activities": 3
  },
  "iati-activity/reporting-org/narrative/@{http://www.w3.org/XML/1998/namespace}lang": {
    "tbalert-activities": 2
  },
  "iati-activity/sector": {
    "tbalert-activities": 3
  },
  "iati-activity/sector/@code": {
    "tbalert-activities": 3
  },
  "iati-activity/sector/@percentage": {
    "tbalert-activities": 3
  },
  "iati-activity/sector/@vocabulary": {
    "tbalert-activities": 3
  },
  "iati-activity/sector/narrative": {
    "tbalert-activities": 1
  },
  "iati-activity/sector/narrative/@{http://www.w3.org/XML/1998/namespace}lang": {
    "tbalert-activities": 1
  },
  "iati-activity/title": {
    "tbalert-activities": 3
  },
  "iati-activity/title/narrative": {
    "tbalert-activities": 3
  },
  "iati-activity/title/narrative/@{http://www.w3.org/XML/1998/namespace}lang": {
    "tbalert-activities": 1
  },
  "iati-activity/transaction": {
    "tbalert-activities": 88
  },
  "iati-activity/transaction/@ref": {
    "tbalert-activities": 79
  },
  "iati-activity/transaction/aid-type": {
    "tbalert-activities": 5
  },
  "iati-activity/transaction/aid-type/@code": {
    "tbalert-activities": 5
  },
  "iati-activity/transaction/description": {
    "tbalert-activities": 12
  },
  "iati-activity/transaction/description/narrative": {
    "tbalert-activities": 12
  },
  "iati-activity/transaction/disbursement-channel": {
    "tbalert-activities": 5
  },
  "iati-activity/transaction/disbursement-channel/@code": {
    "tbalert-activities": 5
  },
  "iati-activity/transaction/finance-type": {
    "tbalert-activities": 2
  },
  "iati-activity/transaction/finance-type/@code": {
    "tbalert-activities": 2
  },
  "iati-activity/transaction/flow-type": {
    "tbalert-activities": 7
  },
  "iati-activity/transaction/flow-type/@code": {
    "tbalert-activities": 7
  },
  "iati-activity/transaction/provider-org": {
    "tbalert-activities": 88
  },
  "iati-activity/transaction/provider-org/@provider-activity-id": {
    "tbalert-activities": 3
  },
  "iati-activity/transaction/provider-org/@ref": {
    "tbalert-activities": 88
  },
  "iati-activity/transaction/provider-org/narrative": {
    "tbalert-activities": 44
  },
  "iati-activity/transaction/provider-org/narrative/@{http://www.w3.org/XML/1998/namespace}lang": {
    "tbalert-activities": 7
  },
  "iati-activity/transaction/receiver-org": {
    "tbalert-activities": 74
  },
  "iati-activity/transaction/receiver-org/@receiver-activity-id": {
    "tbalert-activities": 1
  },
  "iati-activity/transaction/receiver-org/@ref": {
    "tbalert-activities": 49
  },
  "iati-activity/transaction/receiver-org/narrative": {
    "tbalert-activities": 54
  },
  "iati-activity/transaction/receiver-org/narrative/@{http://www.w3.org/XML/1998/namespace}lang": {
    "tbalert-activities": 16
  },
  "iati-activity/transaction/transaction-date": {
    "tbalert-activities": 88
  },
  "iati-activity/transaction/transaction-date/@iso-date": {
    "tbalert-activities": 88
  },
  "iati-activity/transaction/transaction-type": {
    "tbalert-activities": 88
  },
  "iati-activity/transaction/transaction-type/@code": {
    "tbalert-activities": 88
  },
  "iati-activity/transaction/value": {
    "tbalert-activities": 88
  },
  "iati-activity/transaction/value/@currency": {
    "tbalert-activities": 52
  },
  "iati-activity/transaction/value/@value-date": {
    "tbalert-activities": 75
  },
  "iati-organisation": {
    "tbalert-org": 1
  },
  "iati-organisation/@default-currency": {
    "tbalert-org": 1
  },
  "iati-organisation/@last-updated-datetime": {
    "tbalert-org": 1
  },
  "iati-organisation/@{http://www.w3.org/XML/1998/namespace}lang": {
    "tbalert-org": 1
  },
  "iati-organisation/document-link": {
    "tbalert-org": 1
  },
  "iati-organisation/document-link/@format": {
    "tbalert-org": 1
  },
  "iati-organisation/document-link/@url": {
    "tbalert-org": 1
  },
  "iati-organisation/document-link/category": {
    "tbalert-org": 1
  },
  "iati-organisation/document-link/category/@code": {
    "tbalert-org": 1
  },
  "iati-organisation/document-link/language": {
    "tbalert-org": 1
  },
  "iati-organisation/document-link/language/@code": {
    "tbalert-org": 1
  },
  "iati-organisation/document-link/title": {
    "tbalert-org": 1
  },
  "iati-organisation/document-link/title/narrative": {
    "tbalert-org": 1
  },
  "iati-organisation/document-link/title/narrative/@{http://www.w3.org/XML/1998/namespace}lang": {
    "tbalert-org": 1
  },
  "iati-organisation/name": {
    "tbalert-org": 1
  },
  "iati-organisation/name/narrative": {
    "tbalert-org": 1
  },
  "iati-organisation/organisation-identifier": {
    "tbalert-org": 1
  },
  "iati-organisation/reporting-org": {
    "tbalert-org": 1
  },
  "iati-organisation/reporting-org/@ref": {
    "tbalert-org": 1
  },
  "iati-organisation/reporting-org/@type": {
    "tbalert-org": 1
  },
  "iati-organisation/reporting-org/narrative": {
    "tbalert-org": 1
  },
  "iati-organisation/reporting-org/narrative/@{http://www.w3.org/XML/1998/namespace}lang": {
    "tbalert-org": 1
  },
  "iati-organisation/total-budget": {
    "tbalert-org": 1
  },
  "iati-organisation/total-budget/@status": {
    "tbalert-org": 1
  },
  "iati-organisation/total-budget/period-end": {
    "tbalert-org": 1
  },
  "iati-organisation/total-budget/period-end/@iso-date": {
    "tbalert-org": 1
  },
  "iati-organisation/total-budget/period-start": {
    "tbalert-org": 1
  },
  "iati-organisation/total-budget/period-start/@iso-date": {
    "tbalert-org": 1
  },
  "iati-organisation/total-budget/value": {
    "tbalert-org": 1
  },
  "iati-organisation/total-budget/value/@currency": {
    "tbalert-org": 1
  },
  "iati-organisation/total-budget/value/@value-date": {
    "tbalert-org": 1
  }
}