{
  "1": {
    ".//@default-currency": {
      "GBP": 13
    },
    ".//activity-date/@type": {
      "start-actual": 13,
      "end-planned": 13
    },
    ".//activity-status/@code": {
      "2": 13
    },
    ".//default-aid-type/@code": {
      "C01": 13
    },
    ".//default-finance-type/@code": {
      "110": 13
    },
    ".//default-flow-type/@code": {
      "30": 13
    },
    ".//default-tied-status/@code": {
      "5": 13
    },
    ".//participating-org/@role": {
      "Funding": 13,
      "Implementing": 13
    },
    ".//recipient-country/@code": {
      "PS": 13
    },
    ".//reporting-org/@type": {
      "21": 13
    },
    ".//sector[@vocabulary = 'DAC' or not(@vocabulary)]/@code": {
      "14030": 1,
      "32130": 2,
      "15220": 4,
      "92030": 2,
      "99810": 3,
      "15160": 4,
      "11330": 3,
      "15150": 3,
      "43040": 3
    },
    ".//sector/@vocabulary": {
      "RO": 13,
      "DAC": 25
    },
    ".//transaction/transaction-type/@code": {
      "IF": 29,
      "D": 19
    },
    ".//@xml:lang": {
      "en": 14
    }
  }
}