{
  "AU-5-INI855-JO": 1,
  "AU-5-INJ285-JO": 1,
  "AU-5-INJ522-JO": 1,
  "AU-5-INJ678-JO": 1,
  "AU-5-INJ691-JO": 1,
  "AU-5-INJ748-JO": 1,
  "AU-5-INJ757-JO": 1,
  "AU-5-INJ767-JO": 1,
  "AU-5-INK058-JO": 1,
  "AU-5-INK124-JO": 1,
  "AU-5-INK131-JO": 1,
  "AU-5-INK134-JO": 1,
  "AU-5-INK135-JO": 1,
  "AU-5-INK194-JO": 1,
  "AU-5-INK213-JO": 1,
  "AU-5-INK277-JO": 1,
  "AU-5-INK347-JO": 1,
  "AU-5-INK624-JO": 1,
  "AU-5-INK680-JO": 1,
  "AU-5-INK757-JO": 1,
  "AU-5-INL144-JO": 1,
  "AU-5-INL291-JO": 1,
  "AU-5-INL471-JO": 1,
  "AU-5-INL845-JO": 1,
  "AU-5-INL879-JO": 1,
  "AU-5-INL934-JO": 1,
  "AU-5-INM051-JO": 1,
  "AU-5-INM061-JO": 1,
  "AU-5-INM208-JO": 1,
  "AU-5-INM209-JO": 1,
  "AU-5-INM256-JO": 1,
  "AU-5-INM260-JO": 1,
  "AU-5-INM339-JO": 1,
  "AU-5-INM343-JO": 1,
  "AU-5-INM588-JO": 1,
  "AU-5-O14780-JO": 1,
  "AU-5-O14890-JO": 1,
  "AU-5-O15360-JO": 1,
  "AU-5-O15378-JO": 1,
  "AU-5-O16015-JO": 1,
  "AU-5-O16319-JO": 1,
  "AU-5-O16388-JO": 1,
  "AU-5-O16389-JO": 1,
  "AU-5-O16390-JO": 1,
  "AU-5-O16391-JO": 1,
  "AU-5-O16392-JO": 1
}