{
  "2": {
    ".//@default-currency": {
      "ran-activities": {
        "GBP": 1
      }
    },
    ".//activity-date/@type": {
      "ran-activities": {
        "1": 1,
        "2": 1,
        "3": 1
      }
    },
    ".//activity-status/@code": {
      "ran-activities": {
        "2": 1
      }
    },
    ".//description/@type": {
      "ran-activities": {
        "1": 1,
        "2": 1
      }
    },
    ".//participating-org/@role": {
      "ran-activities": {
        "1": 1,
        "3": 1
      }
    },
    ".//participating-org/@type": {
      "ran-activities": {
        "10": 1,
        "70": 1
      }
    },
    ".//recipient-country/@code": {
      "ran-activities": {
        "ID": 1,
        "JP": 1,
        "CN": 1
      }
    },
    ".//recipient-region[@vocabulary = '1' or not(@vocabulary)]/@code": {
      "ran-activities": {
        "89": 1,
        "498": 1
      }
    },
    ".//recipient-region/@vocabulary": {
      "ran-activities": {
        "1": 2
      }
    },
    ".//reporting-org/@type": {
      "ran-activities": {
        "21": 1
      }
    },
    ".//sector[@vocabulary = '1' or not(@vocabulary)]/@code": {
      "ran-activities": {
        "41010": 1
      }
    },
    ".//sector/@vocabulary": {
      "ran-activities": {
        "1": 1
      }
    },
    ".//transaction/provider-org/@type": {
      "ran-activities": {
        "10": 3,
        "70": 7,
        "21": 16
      }
    },
    ".//transaction/receiver-org/@type": {
      "ran-activities": {
        "21": 10,
        "22": 9
      }
    },
    ".//transaction/transaction-type/@code": {
      "ran-activities": {
        "11": 3,
        "1": 7,
        "4": 7,
        "3": 9
      }
    },
    ".//transaction/value/@currency": {
      "ran-activities": {
        "GBP": 17,
        "USD": 9
      }
    },
    ".//@xml:lang": {
      "ran-activities": {
        "en": 10
      }
    }
  }
}