{
  "activity-date": 630,
  "activity-status": 630,
  "activity-website": 0,
  "aid_type": 630,
  "budget": 0,
  "budget_not_provided": 0,
  "capital-spend": 0,
  "conditions_attached": 630,
  "contact-info": 630,
  "country_or_region": 630,
  "description": 356,
  "document-link": 0,
  "iati-identifier": 630,
  "location": 630,
  "location_point_pos": 0,
  "participating-org": 630,
  "recipient_language": 630,
  "reporting-org": 630,
  "result_indicator": 0,
  "sector": 630,
  "sector_dac": 365,
  "title": 630,
  "transaction_commitment": 352,
  "transaction_currency": 630,
  "transaction_spend": 317,
  "transaction_traceability": 293,
  "version": 630
}